pypack/__init__.py
pypack/__main__.py
pypack/c.cpython-39-darwin.so
pypack/convolution.py
pypack/c/fft.h
pypack/c/main.cpp
pypack_template-1.0.1.dist-info/LICENSE
pypack_template-1.0.1.dist-info/METADATA
pypack_template-1.0.1.dist-info/WHEEL
pypack_template-1.0.1.dist-info/entry_points.txt
pypack_template-1.0.1.dist-info/top_level.txt
pypack_template-1.0.1.dist-info/RECORD
