Metadata-Version: 2.1
Name: pypack-template
Version: 1.0.1
Summary: A python package template
Author-email: dy <jealousing@alumni.sjtu.edu.cn>
Requires-Python: >=3.7
License-File: LICENSE
Requires-Dist: numpy
Provides-Extra: dev
Requires-Dist: pytest ; extra == 'dev'
Requires-Dist: pip-tools ; extra == 'dev'
Requires-Dist: pybind11 ; extra == 'dev'
Requires-Dist: build ; extra == 'dev'
Requires-Dist: twine ; extra == 'dev'
